odoo/addons/easy_my_coop_website_taxshelter/README.rst
odoo/addons/easy_my_coop_website_taxshelter/__init__.py
odoo/addons/easy_my_coop_website_taxshelter/__manifest__.py
odoo/addons/easy_my_coop_website_taxshelter/controllers/__init__.py
odoo/addons/easy_my_coop_website_taxshelter/controllers/main.py
odoo/addons/easy_my_coop_website_taxshelter/i18n/easy_my_coop_website_taxshelter.pot
odoo/addons/easy_my_coop_website_taxshelter/readme/CONTRIBUTORS.rst
odoo/addons/easy_my_coop_website_taxshelter/readme/DESCRIPTION.rst
odoo/addons/easy_my_coop_website_taxshelter/static/description/index.html
odoo/addons/easy_my_coop_website_taxshelter/views/easy_my_coop_website_taxshelter_templates.xml
odoo12_addon_easy_my_coop_website_taxshelter-12.0.1.0.0.99.dev17.dist-info/METADATA
odoo12_addon_easy_my_coop_website_taxshelter-12.0.1.0.0.99.dev17.dist-info/WHEEL
odoo12_addon_easy_my_coop_website_taxshelter-12.0.1.0.0.99.dev17.dist-info/top_level.txt
odoo12_addon_easy_my_coop_website_taxshelter-12.0.1.0.0.99.dev17.dist-info/RECORD
